CONTRIBUTORS.txt
MANIFEST.in
README.rst
requirements.txt
setup.py
tox.ini
gipsy/__init__.py
gipsy/pages/__init__.py
gipsy/pages/admin.py
gipsy/pages/admin_base.py
gipsy/pages/apps.py
gipsy/pages/forms.py
gipsy/pages/forms_base.py
gipsy/pages/managers.py
gipsy/pages/managers_base.py
gipsy/pages/models.py
gipsy/pages/models_base.py
gipsy/pages/tests.py
gipsy/pages/urls.py
gipsy/pages/views.py
gipsy/pages/views_base.py
gipsy/pages/migrations/0001_initial.py
gipsy/pages/migrations/0002_remove_page_section_ptr.py
gipsy/pages/migrations/0003_remove_page_order.py
gipsy/pages/migrations/0004_auto_20151004_2212.py
gipsy/pages/migrations/__init__.py
gipsy_pages.egg-info/PKG-INFO
gipsy_pages.egg-info/SOURCES.txt
gipsy_pages.egg-info/dependency_links.txt
gipsy_pages.egg-info/namespace_packages.txt
gipsy_pages.egg-info/pbr.json
gipsy_pages.egg-info/requires.txt
gipsy_pages.egg-info/top_level.txt
requirements/base.txt
requirements/dev.txt
requirements/production.txt
requirements/test.txt